CHANGES.rst
LICENSE.txt
MANIFEST.in
README.rst
setup.py
django_idmap.egg-info/PKG-INFO
django_idmap.egg-info/SOURCES.txt
django_idmap.egg-info/dependency_links.txt
django_idmap.egg-info/requires.txt
django_idmap.egg-info/top_level.txt
idmap/__init__.py
idmap/apps.py
idmap/compat.py
idmap/functions.py
idmap/manager.py
idmap/models.py
idmap/queryset.py
idmap/signals.py
idmap/tls.py
idmap/version.py