Metadata-Version: 1.1
Name: django-idmap
Version: 1.0.3
Summary: An identity mapper for the Django ORM
Home-page: https://bitbucket.org/tkhyn/django-idmap
Author: Thomas Khyn
Author-email: thomas@ksytek.com
License: UNKNOWN
Keywords: django,identity,mapper
Platform: UNKNOWN
Classifier: Programming Language :: Python
Classifier: Programming Language :: Python :: 2
Classifier: Programming Language :: Python :: 3
Classifier: Development Status :: 5 - Production/Stable
Classifier: License :: OSI Approved :: BSD License
Classifier: Framework :: Django
Classifier: Intended Audience :: Developers
Classifier: Operating System :: OS Independent
Classifier: Topic :: Software Development
Classifier: Topic :: Database
